daypilot/__init__.py
daypilot/utils.py
daypilot/server/mcp/__init__.py
daypilot/server/mcp/prompt.py
daypilot/server/router/__init__.py
daypilot/server/router/prompt.py
daypilot-0.1.0.dist-info/METADATA
daypilot-0.1.0.dist-info/WHEEL
daypilot-0.1.0.dist-info/top_level.txt
daypilot-0.1.0.dist-info/RECORD
